gn2pg/__init__.py
gn2pg/api.py
gn2pg/app/__init__.py
gn2pg/app/admin_views.py
gn2pg/app/app.py
gn2pg/app/config.py
gn2pg/app/database.py
gn2pg/app/env.py
gn2pg/app/index.py
gn2pg/app/models.py
gn2pg/app/static/css/custom_flaks_admin.css
gn2pg/app/static/img/src_gn2pg.png
gn2pg/app/templates/admin/master.html
gn2pg/app/templates/index.html
gn2pg/app/utils/__init__.py
gn2pg/app/utils/admin_views.py
gn2pg/check_conf.py
gn2pg/data/__init__.py
gn2pg/data/gn2pgconfig.toml
gn2pg/data/to_gnsynthese.sql
gn2pg/download.py
gn2pg/env.py
gn2pg/helpers.py
gn2pg/locale/en_US/LC_MESAGES/gn2pg.po
gn2pg/locale/fr_FR/LC_MESSAGES/gn2pg.po
gn2pg/locale/fr_FR/LC_MESSAGES/gn2pg.po~
gn2pg/logger.py
gn2pg/main.py
gn2pg/store_postgresql.py
gn2pg/utils.py
gn2pg_client-1.9.1.dist-info/LICENSE
gn2pg_client-1.9.1.dist-info/METADATA
gn2pg_client-1.9.1.dist-info/WHEEL
gn2pg_client-1.9.1.dist-info/entry_points.txt
gn2pg_client-1.9.1.dist-info/RECORD
