Metadata-Version: 2.3
Name: gn2pg_client
Version: 1.9.1
Summary: Import tool from GeoNature to a PostgreSQL database through Export module API (client side)
License: AGPL-3.0-or-later
Keywords: GeoNature,Export,SINP,opendata,biodiversity
Author: Collectif
Maintainer: lpofredc
Maintainer-email: frederic.cloitre@lpo.fr
Requires-Python: >=3.9,<4.0
Classifier: Development Status :: 1 - Planning
Classifier: Environment :: Console
Classifier: Intended Audience :: Developers
Classifier: License :: OSI Approved :: GNU Affero General Public License v3
Classifier: License :: OSI Approved :: GNU Affero General Public License v3 or later (AGPLv3+)
Classifier: Natural Language :: French
Classifier: Operating System :: OS Independent
Classifier: Programming Language :: Python :: 3
Classifier: Programming Language :: Python :: 3.9
Classifier: Programming Language :: Python :: 3.10
Classifier: Programming Language :: Python :: 3.11
Classifier: Programming Language :: Python :: 3.12
Classifier: Programming Language :: Python :: 3.13
Classifier: Programming Language :: Python :: 3.8
Classifier: Programming Language :: Python :: Implementation :: PyPy
Classifier: Topic :: Documentation
Classifier: Topic :: Software Development :: Libraries :: Python Modules
Classifier: Topic :: System :: Installation/Setup
Classifier: Topic :: System :: Software Distribution
Provides-Extra: dashboard
Requires-Dist: coloredlogs (>=0.0.0)
Requires-Dist: flask (>=2,<3) ; extra == "dashboard"
Requires-Dist: flask-admin (>=1,<2) ; extra == "dashboard"
Requires-Dist: flask-sqlalchemy (>=3,<4) ; extra == "dashboard"
Requires-Dist: gunicorn (>=0.0.0) ; extra == "dashboard"
Requires-Dist: psycopg2-binary (>=2,<3)
Requires-Dist: python-decouple (>=3.8,<4.0) ; extra == "dashboard"
Requires-Dist: python-dotenv (>=1,<2) ; extra == "dashboard"
Requires-Dist: requests (>=2,<3)
Requires-Dist: schema (>=0,<1)
Requires-Dist: sqlalchemy (>=1,<2)
Requires-Dist: toml (>=0,<1)
Project-URL: Documentation, https://lpoaura.github.io/GN2PG/
Project-URL: Homepage, https://github.com/lpoaura/gn2gn_client/
